logyca_ai/__init__.py
logyca_ai/assets_for_examples/__init__.py
logyca_ai/assets_for_examples/conversation_samples.py
logyca_ai/assets_for_examples/file_or_documents/__init__.py
logyca_ai/assets_for_examples/file_or_documents/image_base64.py
logyca_ai/assets_for_examples/file_or_documents/ms_excel_base64.py
logyca_ai/assets_for_examples/file_or_documents/ms_word_base64.py
logyca_ai/assets_for_examples/file_or_documents/pdf_base64.py
logyca_ai/assets_for_examples/file_or_documents/plain_text_base64.py
logyca_ai/utils/__init__.py
logyca_ai/utils/constants/__init__.py
logyca_ai/utils/constants/content.py
logyca_ai/utils/constants/image.py
logyca_ai/utils/constants/ocr.py
logyca_ai/utils/helpers/__init__.py
logyca_ai/utils/helpers/azure_openai_chatgpt.py
logyca_ai/utils/helpers/content_loaders.py
logyca_ai/utils/helpers/garbage_collector_helper.py
logyca_ai/utils/helpers/general_utils.py
logyca_ai/utils/helpers/text_extraction_microsoft.py
logyca_ai/utils/helpers/text_extraction_pdf.py
logyca_ai/utils/helpers/tokeniser_helper.py
logyca_ai/utils/schemes/__init__.py
logyca_ai/utils/schemes/input/__init__.py
logyca_ai/utils/schemes/input/conversations.py
logyca_ai/utils/schemes/output/__init__.py
logyca_ai/utils/schemes/output/conversations.py
logyca_ai-0.2.10.dist-info/LICENSE.txt
logyca_ai-0.2.10.dist-info/METADATA
logyca_ai-0.2.10.dist-info/WHEEL
logyca_ai-0.2.10.dist-info/top_level.txt
logyca_ai-0.2.10.dist-info/RECORD
