Metadata-Version: 2.2
Name: logyca-ai
Version: 0.2.10
Summary: An integration package created by the company LOGYCA to interact with ChatGPT and analyze documents, files and other functionality of the OpenAI library.
Home-page: https://github.com/logyca/python-libraries/tree/main/logyca-ai
Author: Jaime Andres Cardona Carrillo
Author-email: jacardona@outlook.com
License: MIT License
Keywords: artificial-intelligence,machine-learning,deep-learning,chatgpt,nlp,language-models,openai,transformers,neural-networks,ai-tools,mlops,data-science,python,data-analysis,automation
Classifier: Development Status :: 4 - Beta
Classifier: Intended Audience :: Developers
Classifier: Intended Audience :: Information Technology
Classifier: Intended Audience :: System Administrators
Classifier: License :: OSI Approved :: MIT License
Classifier: Operating System :: OS Independent
Classifier: Programming Language :: Python :: 3 :: Only
Classifier: Programming Language :: Python :: 3.10
Classifier: Programming Language :: Python :: 3.11
Classifier: Programming Language :: Python :: 3.7
Classifier: Programming Language :: Python :: 3.8
Classifier: Programming Language :: Python :: 3.9
Classifier: Programming Language :: Python :: 3
Classifier: Programming Language :: Python
Classifier: Topic :: Database
Classifier: Topic :: Database :: Front-Ends
Classifier: Topic :: Software Development :: Libraries :: Python Modules
Classifier: Topic :: Software Development :: Libraries
Classifier: Topic :: Software Development
Classifier: Typing :: Typed
Requires-Python: >=3.8
License-File: LICENSE.txt
Requires-Dist: pydantic>=2.5
Requires-Dist: openai>=1.37.1
Requires-Dist: logyca>=0.1.17
Requires-Dist: PyMuPDF>=1.23.2
Requires-Dist: pillow>=9.3.0
Requires-Dist: pytesseract>=0.3.9
Requires-Dist: python-docx>=1.1.1
Requires-Dist: openpyxl>=3.1.3
Requires-Dist: pandas>=2.1.2
Requires-Dist: tiktoken>=0.5.1
Dynamic: author
Dynamic: author-email
Dynamic: classifier
Dynamic: description
Dynamic: description-content-type
Dynamic: home-page
Dynamic: keywords
Dynamic: license
Dynamic: requires-dist
Dynamic: requires-python
Dynamic: summary
